llama_index/llms/sambanovacloud/BUILD
llama_index/llms/sambanovacloud/__init__.py
llama_index/llms/sambanovacloud/base.py
llama_index_llms_sambanovacloud-0.4.0.dist-info/METADATA
llama_index_llms_sambanovacloud-0.4.0.dist-info/WHEEL
llama_index_llms_sambanovacloud-0.4.0.dist-info/RECORD
