Metadata-Version: 2.1
Name: llama-index-llms-sambanovacloud
Version: 0.4.0
Summary: llama-index llms sambanova cloud integration
Author: Your Name
Author-email: you@example.com
Requires-Python: >=3.9,<4.0
Classifier: Programming Language :: Python :: 3
Classifier: Programming Language :: Python :: 3.9
Classifier: Programming Language :: Python :: 3.10
Classifier: Programming Language :: Python :: 3.11
Classifier: Programming Language :: Python :: 3.12
Requires-Dist: aiohttp
Requires-Dist: llama-index-core (>=0.12.0,<0.13.0)
Requires-Dist: python-dotenv (>=1.0.1,<2.0.0)
